eyed3/__about__.py
eyed3/__init__.py
eyed3/core.py
eyed3/main.py
eyed3/mimetype.py
eyed3/id3/__init__.py
eyed3/id3/apple.py
eyed3/id3/frames.py
eyed3/id3/headers.py
eyed3/id3/tag.py
eyed3/mp3/__init__.py
eyed3/mp3/headers.py
eyed3/plugins/__init__.py
eyed3/plugins/_display_parser.py
eyed3/plugins/art.py
eyed3/plugins/classic.py
eyed3/plugins/display.py
eyed3/plugins/extract.py
eyed3/plugins/fixup.py
eyed3/plugins/genres.py
eyed3/plugins/itunes.py
eyed3/plugins/jsontag.py
eyed3/plugins/lameinfo.py
eyed3/plugins/lastfm.py
eyed3/plugins/mimetype.py
eyed3/plugins/nfo.py
eyed3/plugins/pymod.py
eyed3/plugins/stats.py
eyed3/plugins/xep_118.py
eyed3/plugins/yamltag.py
eyed3/utils/__init__.py
eyed3/utils/art.py
eyed3/utils/binfuncs.py
eyed3/utils/console.py
eyed3/utils/log.py
eyed3/utils/prompt.py
eyeD3-0.9.5.dist-info/LICENSE
eyeD3-0.9.5.dist-info/METADATA
eyeD3-0.9.5.dist-info/WHEEL
eyeD3-0.9.5.dist-info/entry_points.txt
eyeD3-0.9.5.dist-info/top_level.txt
eyeD3-0.9.5.dist-info/RECORD
