Metadata-Version: 2.1
Name: eyeD3
Version: 0.9.5
Summary: Python audio data toolkit (ID3 and MP3)
Home-page: http://eyed3.nicfit.net/
Author: Travis Shirk
Author-email: travis@pobox.com
License: GNU GPL v3.0
Download-URL: https://github.com/nicfit/eyeD3/releases/downloads/v0.9.5/eyeD3-0.9.5.tar.gz
Keywords: id3,mp3,python
Platform: Any
Classifier: Environment :: Console
Classifier: Intended Audience :: End Users/Desktop
Classifier: Topic :: Multimedia :: Sound/Audio :: Editors
Classifier: Topic :: Software Development :: Libraries :: Python Modules
Classifier: Intended Audience :: Developers
Classifier: Operating System :: POSIX
Classifier: Natural Language :: English
Classifier: License :: OSI Approved :: GNU General Public License v3 (GPLv3)
Classifier: Programming Language :: Python
Classifier: Programming Language :: Python :: 3.6
Classifier: Programming Language :: Python :: 3.7
Classifier: Programming Language :: Python :: 3.8
Classifier: Development Status :: 5 - Production/Stable
Provides-Extra: display-plugin
Provides-Extra: art-plugin
Provides-Extra: yaml-plugin
